regis/__init__.py
regis_py-0.0.3.dist-info/LICENSE
regis_py-0.0.3.dist-info/METADATA
regis_py-0.0.3.dist-info/WHEEL
regis_py-0.0.3.dist-info/RECORD
