Metadata-Version: 2.1
Name: regis-py
Version: 0.0.3
Summary: Global registry for your objects.
Author: Your Name
Author-email: e.uvarov@me.com
Requires-Python: >=3.8,<4.0
Classifier: Programming Language :: Python :: 3
Classifier: Programming Language :: Python :: 3.8
Classifier: Programming Language :: Python :: 3.9
Classifier: Programming Language :: Python :: 3.10
Classifier: Programming Language :: Python :: 3.11
